clone_detect/__init__.py
clone_detect/cli.py
clone_detect/remover.py
clone_detect/scanner.py
clone_detect/utils.py
clone_detect-0.1.dist-info/METADATA
clone_detect-0.1.dist-info/WHEEL
clone_detect-0.1.dist-info/entry_points.txt
clone_detect-0.1.dist-info/top_level.txt
clone_detect-0.1.dist-info/RECORD
