Metadata-Version: 2.4
Name: clone-detect
Version: 0.1
Summary: Find duplicate files by content hash
Home-page: https://github.com/yourusername/clone-detect
Author: Naila
License: MIT
Keywords: duplicate files,hash,dedupe,cleaner
Requires-Python: >=3.7
Dynamic: author
Dynamic: description
Dynamic: description-content-type
Dynamic: home-page
Dynamic: keywords
Dynamic: license
Dynamic: requires-python
Dynamic: summary
